namedtuple_table/__init__.py
namedtuple_table-0.1.0.post2.dist-info/licenses/LICENSE
namedtuple_table-0.1.0.post2.dist-info/WHEEL
namedtuple_table-0.1.0.post2.dist-info/METADATA
namedtuple_table-0.1.0.post2.dist-info/RECORD
