Metadata-Version: 2.4
Name: namedtuple-table
Version: 0.1.0.post2
Summary: Simple indexable tables using NamedTuple
Keywords: Python,table,index,simple,lightweight
Author: Adam Jackson
Author-email: Adam Jackson <adam.jackson@stfc.ac.uk>
License-Expression: MIT
License-File: LICENSE
Classifier: Development Status :: 4 - Beta
Classifier: Intended Audience :: Developers
Classifier: Programming Language :: Python
Requires-Dist: mypy ; extra == 'lint'
Requires-Dist: ruff ; extra == 'lint'
Requires-Dist: pytest ; extra == 'test'
Maintainer: Adam Jackson
Maintainer-email: Adam Jackson <adam.jackson@stfc.ac.uk>
Requires-Python: >=3.12
Project-URL: Repository, https://github.com/ajjackson/namedtuple-table
Provides-Extra: lint
Provides-Extra: test
